jademagic.py
jademagic-0.1.0.dist-info/DESCRIPTION.rst
jademagic-0.1.0.dist-info/METADATA
jademagic-0.1.0.dist-info/RECORD
jademagic-0.1.0.dist-info/WHEEL
jademagic-0.1.0.dist-info/metadata.json
jademagic-0.1.0.dist-info/top_level.txt
