Metadata-Version: 2.0
Name: jademagic
Version: 0.1.0
Summary: a Jade ne Pug magic for IPython notebooks
Home-page: http://github.com/bollwyvl/jademagic
Author: Nicholas Bollweg
Author-email: nick.bollweg@gmail.com
License: BSD
Keywords: IPython Jade Pug Jupyter
Platform: UNKNOWN
Classifier: Topic :: Utilities
Classifier: Framework :: IPython
Classifier: Natural Language :: English
Classifier: Programming Language :: Python
Classifier: Intended Audience :: Developers
Classifier: Development Status :: 3 - Alpha
Classifier: Operating System :: OS Independent
Classifier: Programming Language :: Python :: 3
Classifier: License :: OSI Approved :: BSD License
Classifier: Topic :: Software Development :: Testing
Requires-Dist: pyjade
